aiohelp/__init__.py
bash-colors/__init__.py
bash-colors/colors.py
bashcolors/__init__.py
bashcolors/colors.py
aiohelp-1.1.dist-info/METADATA
aiohelp-1.1.dist-info/WHEEL
aiohelp-1.1.dist-info/top_level.txt
aiohelp-1.1.dist-info/RECORD
